djangorestframework_expiring_authtoken-0.1.4.dist-info/DESCRIPTION.rst
djangorestframework_expiring_authtoken-0.1.4.dist-info/METADATA
djangorestframework_expiring_authtoken-0.1.4.dist-info/RECORD
djangorestframework_expiring_authtoken-0.1.4.dist-info/WHEEL
djangorestframework_expiring_authtoken-0.1.4.dist-info/metadata.json
djangorestframework_expiring_authtoken-0.1.4.dist-info/top_level.txt
rest_framework_expiring_authtoken/__init__.py
rest_framework_expiring_authtoken/authentication.py
rest_framework_expiring_authtoken/models.py
rest_framework_expiring_authtoken/settings.py
rest_framework_expiring_authtoken/views.py
rest_framework_expiring_authtoken/migrations/0001_initial.py
rest_framework_expiring_authtoken/migrations/__init__.py
