Metadata-Version: 1.1
Name: djangorestframework-expiring-authtoken
Version: 0.1.4
Summary: Expiring Authentication Tokens for Django REST Framework
Home-page: https://github.com/JamesRitchie/django-rest-framework-expiring-tokens
Author: James Ritchie
Author-email: james.a.ritchie@gmail.com
License: BSD
Platform: UNKNOWN
Classifier: Development Status :: 5 - Production/Stable
Classifier: Environment :: Web Environment
Classifier: Framework :: Django
Classifier: Intended Audience :: Developers
Classifier: License :: OSI Approved :: BSD License
Classifier: Operating System :: OS Independent
Classifier: Programming Language :: Python :: 2
Classifier: Programming Language :: Python :: 2.6
Classifier: Programming Language :: Python :: 2.7
Classifier: Programming Language :: Python :: 3
Classifier: Programming Language :: Python :: 3.2
Classifier: Programming Language :: Python :: 3.3
Classifier: Programming Language :: Python :: 3.4
Classifier: Topic :: Internet :: WWW/HTTP
